<annotation>
	<folder></folder>
	<filename>121_jpg.rf.1aa1afed54d2f20405b1fd5117aeebc3.jpg</filename>
	<path>121_jpg.rf.1aa1afed54d2f20405b1fd5117aeebc3.jpg</path>
	<source>
		<database>roboflow.com</database>
	</source>
	<size>
		<width>428</width>
		<height>640</height>
		<depth>3</depth>
	</size>
	<segmented>0</segmented>
	<object>
		<name>crosswalk-sign</name>
		<pose>Unspecified</pose>
		<truncated>0</truncated>
		<difficult>0</difficult>
		<occluded>0</occluded>
		<bndbox>
			<xmin>347</xmin>
			<xmax>421</xmax>
			<ymin>279</ymin>
			<ymax>353</ymax>
		</bndbox>
	</object>
	<object>
		<name>crosswalk-sign</name>
		<pose>Unspecified</pose>
		<truncated>0</truncated>
		<difficult>0</difficult>
		<occluded>0</occluded>
		<bndbox>
			<xmin>3</xmin>
			<xmax>77</xmax>
			<ymin>255</ymin>
			<ymax>331</ymax>
		</bndbox>
	</object>
</annotation>
