<annotation>
	<folder></folder>
	<filename>1705165224742_jpg.rf.e181cc7fa5928633eb5d8dbd3f3117c1.jpg</filename>
	<path>1705165224742_jpg.rf.e181cc7fa5928633eb5d8dbd3f3117c1.jpg</path>
	<source>
		<database>roboflow.com</database>
	</source>
	<size>
		<width>817</width>
		<height>468</height>
		<depth>3</depth>
	</size>
	<segmented>0</segmented>
	<object>
		<name>person</name>
		<pose>Unspecified</pose>
		<truncated>0</truncated>
		<difficult>0</difficult>
		<occluded>0</occluded>
		<bndbox>
			<xmin>130</xmin>
			<xmax>409</xmax>
			<ymin>89</ymin>
			<ymax>442</ymax>
		</bndbox>
	</object>
	<object>
		<name>person</name>
		<pose>Unspecified</pose>
		<truncated>0</truncated>
		<difficult>0</difficult>
		<occluded>0</occluded>
		<bndbox>
			<xmin>445</xmin>
			<xmax>731</xmax>
			<ymin>18</ymin>
			<ymax>440</ymax>
		</bndbox>
	</object>
</annotation>
