<annotation>
	<folder></folder>
	<filename>1766_png.rf.dd32f531594d647843d6d45cbacacb4f.jpg</filename>
	<path>1766_png.rf.dd32f531594d647843d6d45cbacacb4f.jpg</path>
	<source>
		<database>roboflow.com</database>
	</source>
	<size>
		<width>416</width>
		<height>416</height>
		<depth>3</depth>
	</size>
	<segmented>0</segmented>
	<object>
		<name>pole</name>
		<pose>Unspecified</pose>
		<truncated>0</truncated>
		<difficult>0</difficult>
		<occluded>0</occluded>
		<bndbox>
			<xmin>194</xmin>
			<xmax>248</xmax>
			<ymin>163</ymin>
			<ymax>346</ymax>
		</bndbox>
	</object>
</annotation>
