<annotation>
	<folder></folder>
	<filename>49813656-_jpg.rf.178ff53971265b462dcd38ba9d74c3aa.jpg</filename>
	<path>49813656-_jpg.rf.178ff53971265b462dcd38ba9d74c3aa.jpg</path>
	<source>
		<database>roboflow.com</database>
	</source>
	<size>
		<width>640</width>
		<height>640</height>
		<depth>3</depth>
	</size>
	<segmented>0</segmented>
	<object>
		<name>person</name>
		<pose>Unspecified</pose>
		<truncated>0</truncated>
		<difficult>0</difficult>
		<occluded>0</occluded>
		<bndbox>
			<xmin>27</xmin>
			<xmax>132</xmax>
			<ymin>186</ymin>
			<ymax>581</ymax>
		</bndbox>
	</object>
	<object>
		<name>person</name>
		<pose>Unspecified</pose>
		<truncated>0</truncated>
		<difficult>0</difficult>
		<occluded>0</occluded>
		<bndbox>
			<xmin>281</xmin>
			<xmax>383</xmax>
			<ymin>192</ymin>
			<ymax>595</ymax>
		</bndbox>
	</object>
</annotation>
