<annotation>
	<folder></folder>
	<filename>4984818f1a4c51b41a3cc46a002cb0446a9169c6_jpg.rf.43f27e8561ca78b5ebaa1baad72da978.jpg</filename>
	<path>4984818f1a4c51b41a3cc46a002cb0446a9169c6_jpg.rf.43f27e8561ca78b5ebaa1baad72da978.jpg</path>
	<source>
		<database>roboflow.com</database>
	</source>
	<size>
		<width>640</width>
		<height>640</height>
		<depth>3</depth>
	</size>
	<segmented>0</segmented>
	<object>
		<name>bicycle</name>
		<pose>Unspecified</pose>
		<truncated>0</truncated>
		<difficult>0</difficult>
		<occluded>0</occluded>
		<bndbox>
			<xmin>198</xmin>
			<xmax>255</xmax>
			<ymin>352</ymin>
			<ymax>548</ymax>
		</bndbox>
		<polygon>
			<x1>223.846154</x1>
			<y1>356.92307700000003</y1>
			<x2>212.307692</x2>
			<y2>368.461538</y2>
			<x3>196.923077</x3>
			<y3>433.07692299999997</y3>
			<x4>196.923077</x4>
			<y4>473.07692299999997</y4>
			<x5>206.153846</x5>
			<y5>522.307692</y5>
			<x6>219.230769</x6>
			<y6>543.076923</y6>
			<x7>233.846154</x7>
			<y7>546.923077</y7>
			<x8>246.153846</x8>
			<y8>534.615385</y8>
			<x9>226.153846</x9>
			<y9>520.769231</y9>
			<x10>218.461538</x10>
			<y10>502.307692</y10>
			<x11>226.923077</x11>
			<y11>490.769231</y11>
			<x12>236.923077</x12>
			<y12>488.461538</y12>
			<x13>241.538462</x13>
			<y13>473.07692299999997</y13>
			<x14>244.615385</x14>
			<y14>400.769231</y14>
			<x15>253.846154</x15>
			<y15>368.461538</y15>
			<x16>245.384615</x16>
			<y16>350.769231</y16>
			<x17>223.846154</x17>
			<y17>356.92307700000003</y17>
		</polygon>
	</object>
	<object>
		<name>bicycle</name>
		<pose>Unspecified</pose>
		<truncated>0</truncated>
		<difficult>0</difficult>
		<occluded>0</occluded>
		<bndbox>
			<xmin>272</xmin>
			<xmax>389</xmax>
			<ymin>376</ymin>
			<ymax>641</ymax>
		</bndbox>
		<polygon>
			<x1>346.076923</x1>
			<y1>640</y1>
			<x2>363.07692299999997</x2>
			<y2>626.923077</y2>
			<x3>375.38461499999994</x3>
			<y3>600.769231</y3>
			<x4>387.692308</x4>
			<y4>499.230769</y4>
			<x5>369.230769</x5>
			<y5>442.307692</y5>
			<x6>359.230769</x6>
			<y6>430.769231</y6>
			<x7>337.692308</x7>
			<y7>426.153846</y7>
			<x8>326.153846</x8>
			<y8>416.153846</y8>
			<x9>329.230769</x9>
			<y9>379.230769</y9>
			<x10>314.615385</x10>
			<y10>375.38461499999994</y10>
			<x11>313.846154</x11>
			<y11>411.538462</y11>
			<x12>300</x12>
			<y12>459.230769</y12>
			<x13>291.538462</x13>
			<y13>461.538462</y13>
			<x14>282.307692</x14>
			<y14>447.692308</y14>
			<x15>276.923077</x15>
			<y15>454.61538500000006</y15>
			<x16>276.923077</x16>
			<y16>477.692308</y16>
			<x17>270.769231</x17>
			<y17>485.38461499999994</y17>
			<x18>276.923077</x18>
			<y18>508.461538</y18>
			<x19>270.769231</x19>
			<y19>516.153846</y19>
			<x20>283.846154</x20>
			<y20>520</y20>
			<x21>298.461538</x21>
			<y21>542.307692</y21>
			<x22>301.538462</x22>
			<y22>590</y22>
			<x23>315.384615</x23>
			<y23>628.461538</y23>
			<x24>326.92307700000003</x24>
			<y24>640</y24>
			<x25>346.076923</x25>
			<y25>640</y25>
		</polygon>
	</object>
</annotation>
