<annotation>
	<folder></folder>
	<filename>72_jpg.rf.2dad09f665f0ae4916436a1a23b2df88.jpg</filename>
	<path>72_jpg.rf.2dad09f665f0ae4916436a1a23b2df88.jpg</path>
	<source>
		<database>roboflow.com</database>
	</source>
	<size>
		<width>640</width>
		<height>640</height>
		<depth>3</depth>
	</size>
	<segmented>0</segmented>
	<object>
		<name>crosswalk</name>
		<pose>Unspecified</pose>
		<truncated>0</truncated>
		<difficult>0</difficult>
		<occluded>0</occluded>
		<bndbox>
			<xmin>84</xmin>
			<xmax>363</xmax>
			<ymin>182</ymin>
			<ymax>531</ymax>
		</bndbox>
		<polygon>
			<x1>83.486649</x1>
			<y1>199.528436</y1>
			<x2>140.172518</x2>
			<y2>529.593093</y2>
			<x3>361.637135</x3>
			<y3>455.445882</y3>
			<x4>330.998029</x4>
			<y4>324.960831</y4>
			<x5>171.024591</x5>
			<y5>180.917996</y5>
			<x6>83.486649</x6>
			<y6>199.528436</y6>
		</polygon>
	</object>
</annotation>
