<annotation>
	<folder></folder>
	<filename>bus-207_jpg.rf.8c5be2f8dfecf768fa378a108bdf0c61.jpg</filename>
	<path>bus-207_jpg.rf.8c5be2f8dfecf768fa378a108bdf0c61.jpg</path>
	<source>
		<database>roboflow.com</database>
	</source>
	<size>
		<width>640</width>
		<height>640</height>
		<depth>3</depth>
	</size>
	<segmented>0</segmented>
	<object>
		<name>bus</name>
		<pose>Unspecified</pose>
		<truncated>0</truncated>
		<difficult>0</difficult>
		<occluded>0</occluded>
		<bndbox>
			<xmin>10</xmin>
			<xmax>584</xmax>
			<ymin>215</ymin>
			<ymax>641</ymax>
		</bndbox>
		<polygon>
			<x1>519.002694</x1>
			<y1>586.048472</y1>
			<x2>581.362985</x2>
			<y2>572.56059</y2>
			<x3>583.197111</x3>
			<y3>458.587987</y3>
			<x4>561.187597</x4>
			<y4>432.286618</y4>
			<x5>548.348713</x5>
			<y5>430.263435</y5>
			<x6>531.841577</x6>
			<y6>437.007376</y6>
			<x7>500.661432</x7>
			<y7>450.495258</y7>
			<x8>490.573738</x8>
			<y8>460.611169</y8>
			<x9>474.066602</x9>
			<y9>466.006322</y9>
			<x10>452.057087</x10>
			<y10>482.866175</y10>
			<x11>430.964636</x11>
			<y11>475.44784</y11>
			<x12>419.042815</x12>
			<y12>462.634352</y12>
			<x13>440.135267</x13>
			<y13>439.704953</y13>
			<x14>413.540436</x14>
			<y14>440.379347</y14>
			<x15>401.618616</x15>
			<y15>429.589041</y15>
			<x16>377.774976</x16>
			<y16>424.193888</y16>
			<x17>364.019029</x17>
			<y17>426.891465</y17>
			<x18>327.336505</x18>
			<y18>441.728135</y18>
			<x19>290.653981</x19>
			<y19>443.076923</y19>
			<x20>268.644466</x20>
			<y20>432.286618</y20>
			<x21>268.644466</x21>
			<y21>401.264489</y21>
			<x22>288.819855</x22>
			<y22>384.404637</y22>
			<x23>320</x23>
			<y23>383.730242</y23>
			<x24>345.677767</x24>
			<y24>380.358272</y24>
			<x25>364.019029</x25>
			<y25>352.708114</y25>
			<x26>359.433714</x26>
			<y26>343.940991</y26>
			<x27>349.346019</x27>
			<y27>341.243414</y27>
			<x28>331.004757</x28>
			<y28>354.056902</y28>
			<x29>291.571044</x29>
			<y29>350.010537</y29>
			<x30>284.234539</x30>
			<y30>338.545838</y30>
			<x31>274.146845</x31>
			<y31>331.801897</y31>
			<x32>225.5425</x32>
			<y32>331.801897</y32>
			<x33>200.781796</x33>
			<y33>331.127503</y33>
			<x34>196.196481</x34>
			<y34>323.709168</y34>
			<x35>198.030607</x35>
			<y35>305.500527</y35>
			<x36>197.113544</x36>
			<y36>288.640674</y36>
			<x37>217.288932</x37>
			<y37>287.96628</y37>
			<x38>232.879005</x38>
			<y38>273.804004</y38>
			<x39>269.561529</x39>
			<y39>273.804004</y39>
			<x40>272.312718</x40>
			<y40>265.036881</y40>
			<x41>292.488107</x41>
			<y41>263.013698</y41>
			<x42>291.571044</x42>
			<y42>254.246575</y42>
			<x43>275.980971</x43>
			<y43>254.246575</y43>
			<x44>270.478592</x44>
			<y44>247.502634</y44>
			<x45>252.13733</x45>
			<y45>230.642782</y45>
			<x46>246.634952</x46>
			<y46>225.247629</y46>
			<x47>221.874248</x47>
			<y47>224.573235</y47>
			<x48>216.371869</x48>
			<y48>213.782929</y48>
			<x49>149.426262</x49>
			<y49>215.131717</y49>
			<x50>115.494928</x50>
			<y50>265.036881</y50>
			<x51>46.715195</x51>
			<y51>369.567967</y51>
			<x52>9.115607</x52>
			<y52>428.914647</y52>
			<x53>14.617986</x53>
			<y53>509.841939</y53>
			<x54>36.627501</x54>
			<y54>637.976818</y54>
			<x55>137.504442</x55>
			<y55>640</y55>
			<x56>317.248811</x56>
			<y56>639.325606</y56>
			<x57>328.253568</x57>
			<y57>623.814542</y57>
			<x58>352.097208</x58>
			<y58>622.465754</y58>
			<x59>370.438471</x59>
			<y59>616.396207</y59>
			<x60>386.945607</x60>
			<y60>619.768177</y60>
			<x61>400.701553</x61>
			<y61>611.001054</y61>
			<x62>438.301141</x62>
			<y62>617.744995</y62>
			<x63>462.144781</x63>
			<y63>636.62803</y63>
			<x64>485.071359</x64>
			<y64>633.256059</y64>
			<x65>519.002694</x65>
			<y65>586.048472</y65>
		</polygon>
	</object>
</annotation>
