<annotation>
	<folder></folder>
	<filename>bus-77_jpg.rf.6d6f364cd827b4366832b24dbb82c170.jpg</filename>
	<path>bus-77_jpg.rf.6d6f364cd827b4366832b24dbb82c170.jpg</path>
	<source>
		<database>roboflow.com</database>
	</source>
	<size>
		<width>640</width>
		<height>640</height>
		<depth>3</depth>
	</size>
	<segmented>0</segmented>
	<object>
		<name>bus</name>
		<pose>Unspecified</pose>
		<truncated>0</truncated>
		<difficult>0</difficult>
		<occluded>0</occluded>
		<bndbox>
			<xmin>48</xmin>
			<xmax>622</xmax>
			<ymin>96</ymin>
			<ymax>594</ymax>
		</bndbox>
		<polygon>
			<x1>99.725086</x1>
			<y1>232.943872</y1>
			<x2>114.158075</x2>
			<y2>236.609393</y2>
			<x3>99.725086</x3>
			<y3>298.923253</y3>
			<x4>83.917526</x4>
			<y4>383.230241</y4>
			<x5>79.793815</x5>
			<y5>429.049255</y5>
			<x6>74.982818</x6>
			<y6>459.289805</y6>
			<x7>74.295533</x7>
			<y7>534.432989</y7>
			<x8>123.092783</x8>
			<y8>570.171821</y8>
			<x9>190.446735</x9>
			<y9>590.332188</y9>
			<x10>234.43299</x10>
			<y10>593.081329</y10>
			<x11>367.079038</x11>
			<y11>535.34937</y11>
			<x12>369.140893</x12>
			<y12>549.095075</y12>
			<x13>399.381443</x13>
			<y13>559.175258</y13>
			<x14>421.374571</x14>
			<y14>553.676976</y14>
			<x15>434.43299</x15>
			<y15>517.938144</y15>
			<x16>547.835051</x16>
			<y16>464.788087</y16>
			<x17>553.333333</x17>
			<y17>468.453608</y17>
			<x18>580.137457</x18>
			<y18>468.453608</y18>
			<x19>587.697595</x19>
			<y19>445.5441</y19>
			<x20>618.625429</x20>
			<y20>419.885452</y20>
			<x21>620.687285</x21>
			<y21>352.07331</y21>
			<x22>617.938144</x22>
			<y22>267.766323</y22>
			<x23>611.065292</x23>
			<y23>250.355098</y23>
			<x24>555.395189</x24>
			<y24>220.114548</y24>
			<x25>546.460481</x25>
			<y25>210.034364</y25>
			<x26>378.075601</x26>
			<y26>120.229095</y26>
			<x27>323.780069</x27>
			<y27>94.570447</y27>
			<x28>301.786941</x28>
			<y28>94.570447</y28>
			<x29>222.061856</x29>
			<y29>112.898052</y29>
			<x30>167.079038</x30>
			<y30>138.556701</y30>
			<x31>136.151203</x31>
			<y31>169.713631</y31>
			<x32>123.780069</x32>
			<y32>202.703322</y32>
			<x33>103.848797</x33>
			<y33>201.786941</y33>
			<x34>56.426117</x34>
			<y34>231.111111</y34>
			<x35>47.491409</x35>
			<y35>283.344788</y35>
			<x36>58.487973</x36>
			<y36>303.505155</y36>
			<x37>70.859107</x37>
			<y37>245.773196</y37>
			<x38>99.725086</x38>
			<y38>232.943872</y38>
		</polygon>
	</object>
</annotation>
