<annotation>
	<folder></folder>
	<filename>cf8727ab4fcb1bed2bbb4d860bdbdd59_jpg.rf.ee47b8381d7ef3ac8b321e3ead578a8a.jpg</filename>
	<path>cf8727ab4fcb1bed2bbb4d860bdbdd59_jpg.rf.ee47b8381d7ef3ac8b321e3ead578a8a.jpg</path>
	<source>
		<database>roboflow.com</database>
	</source>
	<size>
		<width>640</width>
		<height>640</height>
		<depth>3</depth>
	</size>
	<segmented>0</segmented>
	<object>
		<name>bus</name>
		<pose>Unspecified</pose>
		<truncated>0</truncated>
		<difficult>0</difficult>
		<occluded>0</occluded>
		<bndbox>
			<xmin>82</xmin>
			<xmax>542</xmax>
			<ymin>21</ymin>
			<ymax>599</ymax>
		</bndbox>
	</object>
</annotation>
