<annotation>
	<folder></folder>
	<filename>e-367-_png_jpg.rf.3060b813e498b3ba0c07b51367853ce7.jpg</filename>
	<path>e-367-_png_jpg.rf.3060b813e498b3ba0c07b51367853ce7.jpg</path>
	<source>
		<database>roboflow.com</database>
	</source>
	<size>
		<width>640</width>
		<height>640</height>
		<depth>3</depth>
	</size>
	<segmented>0</segmented>
	<object>
		<name>bicycle</name>
		<pose>Unspecified</pose>
		<truncated>0</truncated>
		<difficult>0</difficult>
		<occluded>0</occluded>
		<bndbox>
			<xmin>84</xmin>
			<xmax>503</xmax>
			<ymin>268</ymin>
			<ymax>613</ymax>
		</bndbox>
	</object>
</annotation>
