<annotation>
	<folder></folder>
	<filename>p2482120_jpg.rf.8b3ff9acc2bc3a309d37b9b51972aff1.jpg</filename>
	<path>p2482120_jpg.rf.8b3ff9acc2bc3a309d37b9b51972aff1.jpg</path>
	<source>
		<database>roboflow.com</database>
	</source>
	<size>
		<width>640</width>
		<height>640</height>
		<depth>3</depth>
	</size>
	<segmented>0</segmented>
	<object>
		<name>backpack</name>
		<pose>Unspecified</pose>
		<truncated>0</truncated>
		<difficult>0</difficult>
		<occluded>0</occluded>
		<bndbox>
			<xmin>164</xmin>
			<xmax>334</xmax>
			<ymin>388</ymin>
			<ymax>582</ymax>
		</bndbox>
	</object>
	<object>
		<name>backpack</name>
		<pose>Unspecified</pose>
		<truncated>0</truncated>
		<difficult>0</difficult>
		<occluded>0</occluded>
		<bndbox>
			<xmin>218</xmin>
			<xmax>352</xmax>
			<ymin>240</ymin>
			<ymax>354</ymax>
		</bndbox>
	</object>
	<object>
		<name>backpack</name>
		<pose>Unspecified</pose>
		<truncated>0</truncated>
		<difficult>0</difficult>
		<occluded>0</occluded>
		<bndbox>
			<xmin>256</xmin>
			<xmax>358</xmax>
			<ymin>142</ymin>
			<ymax>227</ymax>
		</bndbox>
	</object>
</annotation>
