<annotation>
	<folder></folder>
	<filename>T021000_jpg.rf.05bd935949cf1afc45a492526d1669fe.jpg</filename>
	<path>T021000_jpg.rf.05bd935949cf1afc45a492526d1669fe.jpg</path>
	<source>
		<database>roboflow.com</database>
	</source>
	<size>
		<width>640</width>
		<height>640</height>
		<depth>3</depth>
	</size>
	<segmented>0</segmented>
	<object>
		<name>rail</name>
		<pose>Unspecified</pose>
		<truncated>0</truncated>
		<difficult>0</difficult>
		<occluded>0</occluded>
		<bndbox>
			<xmin>348</xmin>
			<xmax>641</xmax>
			<ymin>360</ymin>
			<ymax>553</ymax>
		</bndbox>
		<polygon>
			<x1>347.004011</x1>
			<y1>382.138658</y1>
			<x2>637.09091</x2>
			<y2>551.757577</y2>
			<x3>640</x3>
			<y3>432.484849</y3>
			<x4>414.060606</x4>
			<y4>358.787878</y4>
			<x5>352</x5>
			<y5>360.727273</y5>
			<x6>347.004011</x6>
			<y6>382.138658</y6>
		</polygon>
	</object>
	<object>
		<name>rail</name>
		<pose>Unspecified</pose>
		<truncated>0</truncated>
		<difficult>0</difficult>
		<occluded>0</occluded>
		<bndbox>
			<xmin>1</xmin>
			<xmax>316</xmax>
			<ymin>391</ymin>
			<ymax>639</ymax>
		</bndbox>
		<polygon>
			<x1>0</x1>
			<y1>638.060606</y1>
			<x2>315.151516</x2>
			<y2>625.454545</y2>
			<x3>261.818182</x3>
			<y3>398.545455</y3>
			<x4>227.878788</x4>
			<y4>389.818182</y4>
			<x5>254.060606</x5>
			<y5>598.303029</y5>
			<x6>160</x6>
			<y6>586.666667</y6>
			<x7>137.696971</x7>
			<y7>447.030304</y7>
			<x8>106.666667</x8>
			<y8>409.212122</y8>
			<x9>0</x9>
			<y9>525.575757</y9>
			<x10>0</x10>
			<y10>638.060606</y10>
		</polygon>
	</object>
</annotation>
