<annotation>
	<folder></folder>
	<filename>T301067_jpg.rf.44831727a50d282d56891494a18826f1.jpg</filename>
	<path>T301067_jpg.rf.44831727a50d282d56891494a18826f1.jpg</path>
	<source>
		<database>roboflow.com</database>
	</source>
	<size>
		<width>640</width>
		<height>640</height>
		<depth>3</depth>
	</size>
	<segmented>0</segmented>
	<object>
		<name>rail</name>
		<pose>Unspecified</pose>
		<truncated>0</truncated>
		<difficult>0</difficult>
		<occluded>0</occluded>
		<bndbox>
			<xmin>110</xmin>
			<xmax>203</xmax>
			<ymin>1</ymin>
			<ymax>137</ymax>
		</bndbox>
		<polygon>
			<x1>109.333333</x1>
			<y1>122.222222</y1>
			<x2>120.444444</x2>
			<y2>132.444444</y2>
			<x3>129.333333</x3>
			<y3>136</y3>
			<x4>138.666667</x4>
			<y4>133.777778</y4>
			<x5>202.222222</x5>
			<y5>0</y5>
			<x6>183.111111</x6>
			<y6>2.222222</y6>
			<x7>111.111111</x7>
			<y7>116.888889</y7>
			<x8>109.333333</x8>
			<y8>122.222222</y8>
		</polygon>
	</object>
	<object>
		<name>rail</name>
		<pose>Unspecified</pose>
		<truncated>0</truncated>
		<difficult>0</difficult>
		<occluded>0</occluded>
		<bndbox>
			<xmin>37</xmin>
			<xmax>111</xmax>
			<ymin>158</ymin>
			<ymax>277</ymax>
		</bndbox>
		<polygon>
			<x1>35.555556</x1>
			<y1>265.333333</y1>
			<x2>36</x2>
			<y2>272.888889</y2>
			<x3>52.888889</x3>
			<y3>276.444444</y3>
			<x4>68.444444</x4>
			<y4>263.555556</y4>
			<x5>106.666667</x5>
			<y5>183.555556</y5>
			<x6>110.222222</x6>
			<y6>171.111111</y6>
			<x7>102.666667</x7>
			<y7>157.333333</y7>
			<x8>96</x8>
			<y8>160.444444</y8>
			<x9>35.555556</x9>
			<y9>265.333333</y9>
		</polygon>
	</object>
	<object>
		<name>rail</name>
		<pose>Unspecified</pose>
		<truncated>0</truncated>
		<difficult>0</difficult>
		<occluded>0</occluded>
		<bndbox>
			<xmin>1</xmin>
			<xmax>70</xmax>
			<ymin>286</ymin>
			<ymax>461</ymax>
		</bndbox>
		<polygon>
			<x1>69.333333</x1>
			<y1>299.111111</y1>
			<x2>25.333333</x2>
			<y2>285.333333</y2>
			<x3>5.333333</x3>
			<y3>316.888889</y3>
			<x4>0</x4>
			<y4>328.444444</y4>
			<x5>0.444444</x5>
			<y5>459.555556</y5>
			<x6>69.333333</x6>
			<y6>299.111111</y6>
		</polygon>
	</object>
	<object>
		<name>rail</name>
		<pose>Unspecified</pose>
		<truncated>0</truncated>
		<difficult>0</difficult>
		<occluded>0</occluded>
		<bndbox>
			<xmin>500</xmin>
			<xmax>641</xmax>
			<ymin>417</ymin>
			<ymax>602</ymax>
		</bndbox>
		<polygon>
			<x1>640</x1>
			<y1>507.111111</y1>
			<x2>596.444444</x2>
			<y2>445.777778</y2>
			<x3>578.222222</x3>
			<y3>435.555556</y3>
			<x4>499.111111</x4>
			<y4>416</y4>
			<x5>499.555556</x5>
			<y5>422.666667</y5>
			<x6>572.444444</x6>
			<y6>551.555556</y6>
			<x7>609.333333</x7>
			<y7>591.111111</y7>
			<x8>635.111111</x8>
			<y8>600.888889</y8>
			<x9>640</x9>
			<y9>591.555556</y9>
			<x10>640</x10>
			<y10>507.111111</y10>
		</polygon>
	</object>
	<object>
		<name>rail</name>
		<pose>Unspecified</pose>
		<truncated>0</truncated>
		<difficult>0</difficult>
		<occluded>0</occluded>
		<bndbox>
			<xmin>278</xmin>
			<xmax>566</xmax>
			<ymin>10</ymin>
			<ymax>410</ymax>
		</bndbox>
		<polygon>
			<x1>457.808948</x1>
			<y1>351.764935</y1>
			<x2>492.920059</x2>
			<y2>393.098268</y2>
			<x3>564.920059</x3>
			<y3>409.098268</y3>
			<x4>560.03117</x4>
			<y4>396.20938</y4>
			<x5>312.920059</x5>
			<y5>48.653824</y5>
			<x6>282.697836</x6>
			<y6>9.542713</y6>
			<x7>276.920059</x7>
			<y7>9.098268</y7>
			<x8>457.808948</x8>
			<y8>351.764935</y8>
		</polygon>
	</object>
</annotation>
