<annotation>
	<folder></folder>
	<filename>image25_jpeg.rf.4986bad048a6f16c8512d1938fb417de.jpg</filename>
	<path>image25_jpeg.rf.4986bad048a6f16c8512d1938fb417de.jpg</path>
	<source>
		<database>roboflow.com</database>
	</source>
	<size>
		<width>640</width>
		<height>640</height>
		<depth>3</depth>
	</size>
	<segmented>0</segmented>
	<object>
		<name>backpack</name>
		<pose>Unspecified</pose>
		<truncated>0</truncated>
		<difficult>0</difficult>
		<occluded>0</occluded>
		<bndbox>
			<xmin>130</xmin>
			<xmax>512</xmax>
			<ymin>38</ymin>
			<ymax>547</ymax>
		</bndbox>
	</object>
</annotation>
