<annotation>
	<folder></folder>
	<filename>maxresdefault-27_jpg.rf.16f4b1f94c21f0d45ba131bea98fe2bd.jpg</filename>
	<path>maxresdefault-27_jpg.rf.16f4b1f94c21f0d45ba131bea98fe2bd.jpg</path>
	<source>
		<database>roboflow.com</database>
	</source>
	<size>
		<width>640</width>
		<height>640</height>
		<depth>3</depth>
	</size>
	<segmented>0</segmented>
	<object>
		<name>truck</name>
		<pose>Unspecified</pose>
		<truncated>0</truncated>
		<difficult>0</difficult>
		<occluded>0</occluded>
		<bndbox>
			<xmin>277</xmin>
			<xmax>490</xmax>
			<ymin>1</ymin>
			<ymax>476</ymax>
		</bndbox>
	</object>
</annotation>
