<annotation>
	<folder></folder>
	<filename>91_jpg.rf.08907cf65e65d91bc9aa21b7e57eba64.jpg</filename>
	<path>91_jpg.rf.08907cf65e65d91bc9aa21b7e57eba64.jpg</path>
	<source>
		<database>roboflow.com</database>
	</source>
	<size>
		<width>640</width>
		<height>640</height>
		<depth>3</depth>
	</size>
	<segmented>0</segmented>
	<object>
		<name>crosswalk</name>
		<pose>Unspecified</pose>
		<truncated>0</truncated>
		<difficult>0</difficult>
		<occluded>0</occluded>
		<bndbox>
			<xmin>1</xmin>
			<xmax>458</xmax>
			<ymin>3</ymin>
			<ymax>626</ymax>
		</bndbox>
		<polygon>
			<x1>0.767128</x1>
			<y1>625.376728</y1>
			<x2>456.691358</x2>
			<y2>124.656453</y2>
			<x3>198.448539</x3>
			<y3>2.334398</y3>
			<x4>0</x4>
			<y4>130.285715</y4>
			<x5>5.337815</x5>
			<y5>130.372437</y5>
			<x6>0.767128</x6>
			<y6>625.376728</y6>
		</polygon>
	</object>
</annotation>
