<annotation>
	<folder></folder>
	<filename>images208_jpg.rf.cac49edbeb134c9f6a340a56fe103ea7.jpg</filename>
	<path>images208_jpg.rf.cac49edbeb134c9f6a340a56fe103ea7.jpg</path>
	<source>
		<database>roboflow.com</database>
	</source>
	<size>
		<width>640</width>
		<height>640</height>
		<depth>3</depth>
	</size>
	<segmented>0</segmented>
	<object>
		<name>pothole</name>
		<pose>Unspecified</pose>
		<truncated>0</truncated>
		<difficult>0</difficult>
		<occluded>0</occluded>
		<bndbox>
			<xmin>50</xmin>
			<xmax>139</xmax>
			<ymin>96</ymin>
			<ymax>195</ymax>
		</bndbox>
		<polygon>
			<x1>125</x1>
			<y1>101.875</y1>
			<x2>120.625</x2>
			<y2>97.5</y2>
			<x3>115.625</x3>
			<y3>95</y3>
			<x4>89.375</x4>
			<y4>105</y4>
			<x5>65.625</x5>
			<y5>116.25</y5>
			<x6>48.75</x6>
			<y6>130.625</y6>
			<x7>48.75</x7>
			<y7>148.125</y7>
			<x8>51.875</x8>
			<y8>151.25</y8>
			<x9>91.875</x9>
			<y9>170</y9>
			<x10>113.125</x10>
			<y10>191.25</y10>
			<x11>128.75</x11>
			<y11>194.375</y11>
			<x12>136.25</x12>
			<y12>185.625</y12>
			<x13>137.5</x13>
			<y13>165.625</y13>
			<x14>122.5</x14>
			<y14>130.625</y14>
			<x15>125</x15>
			<y15>101.875</y15>
		</polygon>
	</object>
	<object>
		<name>pothole</name>
		<pose>Unspecified</pose>
		<truncated>0</truncated>
		<difficult>0</difficult>
		<occluded>0</occluded>
		<bndbox>
			<xmin>2</xmin>
			<xmax>49</xmax>
			<ymin>149</ymin>
			<ymax>227</ymax>
		</bndbox>
		<polygon>
			<x1>36.875</x1>
			<y1>160</y1>
			<x2>3.125</x2>
			<y2>147.5</y2>
			<x3>1.25</x3>
			<y3>225.625</y3>
			<x4>31.25</x4>
			<y4>225.625</y4>
			<x5>40.625</x5>
			<y5>221.25</y5>
			<x6>47.5</x6>
			<y6>210.625</y6>
			<x7>43.75</x7>
			<y7>171.875</y7>
			<x8>36.875</x8>
			<y8>160</y8>
		</polygon>
	</object>
	<object>
		<name>pothole</name>
		<pose>Unspecified</pose>
		<truncated>0</truncated>
		<difficult>0</difficult>
		<occluded>0</occluded>
		<bndbox>
			<xmin>57</xmin>
			<xmax>147</xmax>
			<ymin>215</ymin>
			<ymax>318</ymax>
		</bndbox>
		<polygon>
			<x1>126.875</x1>
			<y1>213.75</y1>
			<x2>108.125</x2>
			<y2>215</y2>
			<x3>78.125</x3>
			<y3>230</y3>
			<x4>62.5</x4>
			<y4>244.375</y4>
			<x5>56.25</x5>
			<y5>260.625</y5>
			<x6>58.75</x6>
			<y6>274.375</y6>
			<x7>70</x7>
			<y7>298.125</y7>
			<x8>94.375</x8>
			<y8>315</y8>
			<x9>135</x9>
			<y9>316.875</y9>
			<x10>143.75</x10>
			<y10>310.625</y10>
			<x11>146.25</x11>
			<y11>300.625</y11>
			<x12>137.5</x12>
			<y12>221.875</y12>
			<x13>126.875</x13>
			<y13>213.75</y13>
		</polygon>
	</object>
	<object>
		<name>pothole</name>
		<pose>Unspecified</pose>
		<truncated>0</truncated>
		<difficult>0</difficult>
		<occluded>0</occluded>
		<bndbox>
			<xmin>21</xmin>
			<xmax>71</xmax>
			<ymin>309</ymin>
			<ymax>353</ymax>
		</bndbox>
		<polygon>
			<x1>68.125</x1>
			<y1>307.5</y1>
			<x2>39.375</x2>
			<y2>307.5</y2>
			<x3>26.875</x3>
			<y3>311.25</y3>
			<x4>20</x4>
			<y4>318.125</y4>
			<x5>20</x5>
			<y5>343.125</y5>
			<x6>37.5</x6>
			<y6>351.875</y6>
			<x7>58.125</x7>
			<y7>341.25</y7>
			<x8>63.75</x8>
			<y8>334.375</y8>
			<x9>70</x9>
			<y9>323.125</y9>
			<x10>68.125</x10>
			<y10>307.5</y10>
		</polygon>
	</object>
	<object>
		<name>pothole</name>
		<pose>Unspecified</pose>
		<truncated>0</truncated>
		<difficult>0</difficult>
		<occluded>0</occluded>
		<bndbox>
			<xmin>176</xmin>
			<xmax>246</xmax>
			<ymin>139</ymin>
			<ymax>187</ymax>
		</bndbox>
		<polygon>
			<x1>238.125</x1>
			<y1>137.5</y1>
			<x2>224.375</x2>
			<y2>137.5</y2>
			<x3>205.625</x3>
			<y3>138.75</y3>
			<x4>191.875</x4>
			<y4>145</y4>
			<x5>191.25</x5>
			<y5>150.625</y5>
			<x6>183.75</x6>
			<y6>154.375</y6>
			<x7>175</x7>
			<y7>178.125</y7>
			<x8>178.125</x8>
			<y8>185</y8>
			<x9>187.5</x9>
			<y9>185.625</y9>
			<x10>229.375</x10>
			<y10>173.75</y10>
			<x11>240</x11>
			<y11>163.125</y11>
			<x12>245</x12>
			<y12>144.375</y12>
			<x13>238.125</x13>
			<y13>137.5</y13>
		</polygon>
	</object>
	<object>
		<name>pothole</name>
		<pose>Unspecified</pose>
		<truncated>0</truncated>
		<difficult>0</difficult>
		<occluded>0</occluded>
		<bndbox>
			<xmin>155</xmin>
			<xmax>187</xmax>
			<ymin>205</ymin>
			<ymax>229</ymax>
		</bndbox>
		<polygon>
			<x1>174.375</x1>
			<y1>203.75</y1>
			<x2>153.75</x2>
			<y2>213.125</y2>
			<x3>160.625</x3>
			<y3>223.75</y3>
			<x4>177.5</x4>
			<y4>228.125</y4>
			<x5>185</x5>
			<y5>223.125</y5>
			<x6>186.25</x6>
			<y6>211.875</y6>
			<x7>181.875</x7>
			<y7>205</y7>
			<x8>174.375</x8>
			<y8>203.75</y8>
		</polygon>
	</object>
	<object>
		<name>pothole</name>
		<pose>Unspecified</pose>
		<truncated>0</truncated>
		<difficult>0</difficult>
		<occluded>0</occluded>
		<bndbox>
			<xmin>137</xmin>
			<xmax>157</xmax>
			<ymin>371</ymin>
			<ymax>407</ymax>
		</bndbox>
		<polygon>
			<x1>136.25</x1>
			<y1>389.375</y1>
			<x2>143.75</x2>
			<y2>395.625</y2>
			<x3>145.625</x3>
			<y3>406.25</y3>
			<x4>156.25</x4>
			<y4>405.625</y4>
			<x5>156.25</x5>
			<y5>373.125</y5>
			<x6>148.125</x6>
			<y6>370</y6>
			<x7>137.5</x7>
			<y7>378.125</y7>
			<x8>136.25</x8>
			<y8>389.375</y8>
		</polygon>
	</object>
	<object>
		<name>pothole</name>
		<pose>Unspecified</pose>
		<truncated>0</truncated>
		<difficult>0</difficult>
		<occluded>0</occluded>
		<bndbox>
			<xmin>127</xmin>
			<xmax>205</xmax>
			<ymin>324</ymin>
			<ymax>367</ymax>
		</bndbox>
		<polygon>
			<x1>186.875</x1>
			<y1>325</y1>
			<x2>174.375</x2>
			<y2>340</y2>
			<x3>155.625</x3>
			<y3>341.25</y3>
			<x4>144.375</x4>
			<y4>341.25</y4>
			<x5>137.5</x5>
			<y5>334.375</y5>
			<x6>136.25</x6>
			<y6>325.625</y6>
			<x7>128.75</x7>
			<y7>325.625</y7>
			<x8>126.25</x8>
			<y8>344.375</y8>
			<x9>133.125</x9>
			<y9>353.75</y9>
			<x10>163.125</x10>
			<y10>360</y10>
			<x11>169.375</x11>
			<y11>351.25</y11>
			<x12>173.75</x12>
			<y12>353.125</y12>
			<x13>175.625</x13>
			<y13>362.5</y13>
			<x14>191.25</x14>
			<y14>365.625</y14>
			<x15>203.75</x15>
			<y15>354.375</y15>
			<x16>203.75</x16>
			<y16>330.625</y16>
			<x17>198.125</x17>
			<y17>322.5</y17>
			<x18>186.875</x18>
			<y18>325</y18>
		</polygon>
	</object>
	<object>
		<name>pothole</name>
		<pose>Unspecified</pose>
		<truncated>0</truncated>
		<difficult>0</difficult>
		<occluded>0</occluded>
		<bndbox>
			<xmin>165</xmin>
			<xmax>185</xmax>
			<ymin>285</ymin>
			<ymax>305</ymax>
		</bndbox>
		<polygon>
			<x1>163.75</x1>
			<y1>296.875</y1>
			<x2>168.125</x2>
			<y2>302.5</y2>
			<x3>178.75</x3>
			<y3>304.375</y3>
			<x4>183.75</x4>
			<y4>301.875</y4>
			<x5>183.75</x5>
			<y5>290.625</y5>
			<x6>166.875</x6>
			<y6>283.75</y6>
			<x7>163.75</x7>
			<y7>296.875</y7>
		</polygon>
	</object>
	<object>
		<name>pothole</name>
		<pose>Unspecified</pose>
		<truncated>0</truncated>
		<difficult>0</difficult>
		<occluded>0</occluded>
		<bndbox>
			<xmin>121</xmin>
			<xmax>204</xmax>
			<ymin>439</ymin>
			<ymax>503</ymax>
		</bndbox>
		<polygon>
			<x1>195.625</x1>
			<y1>442.5</y1>
			<x2>189.375</x2>
			<y2>438.75</y2>
			<x3>164.375</x3>
			<y3>442.5</y3>
			<x4>153.125</x4>
			<y4>437.5</y4>
			<x5>133.75</x5>
			<y5>450.625</y5>
			<x6>120</x6>
			<y6>473.125</y6>
			<x7>120</x7>
			<y7>480.625</y7>
			<x8>131.875</x8>
			<y8>500</y8>
			<x9>143.75</x9>
			<y9>501.875</y9>
			<x10>170.625</x10>
			<y10>492.5</y10>
			<x11>186.25</x11>
			<y11>481.875</y11>
			<x12>202.5</x12>
			<y12>454.375</y12>
			<x13>195.625</x13>
			<y13>442.5</y13>
		</polygon>
	</object>
	<object>
		<name>pothole</name>
		<pose>Unspecified</pose>
		<truncated>0</truncated>
		<difficult>0</difficult>
		<occluded>0</occluded>
		<bndbox>
			<xmin>111</xmin>
			<xmax>177</xmax>
			<ymin>535</ymin>
			<ymax>590</ymax>
		</bndbox>
		<polygon>
			<x1>168.125</x1>
			<y1>536.25</y1>
			<x2>146.875</x2>
			<y2>533.75</y2>
			<x3>123.75</x3>
			<y3>546.875</y3>
			<x4>116.25</x4>
			<y4>558.125</y4>
			<x5>110</x5>
			<y5>580.625</y5>
			<x6>119.375</x6>
			<y6>588.75</y6>
			<x7>156.25</x7>
			<y7>588.125</y7>
			<x8>166.25</x8>
			<y8>583.125</y8>
			<x9>175</x9>
			<y9>565.625</y9>
			<x10>176.25</x10>
			<y10>545.625</y10>
			<x11>168.125</x11>
			<y11>536.25</y11>
		</polygon>
	</object>
	<object>
		<name>pothole</name>
		<pose>Unspecified</pose>
		<truncated>0</truncated>
		<difficult>0</difficult>
		<occluded>0</occluded>
		<bndbox>
			<xmin>159</xmin>
			<xmax>339</xmax>
			<ymin>544</ymin>
			<ymax>641</ymax>
		</bndbox>
		<polygon>
			<x1>330.625</x1>
			<y1>572.5</y1>
			<x2>289.375</x2>
			<y2>575</y2>
			<x3>256.875</x3>
			<y3>550</y3>
			<x4>240.625</x4>
			<y4>542.5</y4>
			<x5>228.125</x5>
			<y5>543.75</y5>
			<x6>175.625</x6>
			<y6>573.75</y6>
			<x7>157.5</x7>
			<y7>606.875</y7>
			<x8>158.75</x8>
			<y8>623.125</y8>
			<x9>171.875</x9>
			<y9>640</y9>
			<x10>305</x10>
			<y10>639.375</y10>
			<x11>307.5</x11>
			<y11>626.875</y11>
			<x12>335</x12>
			<y12>594.375</y12>
			<x13>337.5</x13>
			<y13>576.875</y13>
			<x14>330.625</x14>
			<y14>572.5</y14>
		</polygon>
	</object>
	<object>
		<name>pothole</name>
		<pose>Unspecified</pose>
		<truncated>0</truncated>
		<difficult>0</difficult>
		<occluded>0</occluded>
		<bndbox>
			<xmin>187</xmin>
			<xmax>246</xmax>
			<ymin>467</ymin>
			<ymax>512</ymax>
		</bndbox>
		<polygon>
			<x1>223.125</x1>
			<y1>466.25</y1>
			<x2>200.625</x2>
			<y2>477.5</y2>
			<x3>187.5</x3>
			<y3>490.625</y3>
			<x4>186.25</x4>
			<y4>500.625</y4>
			<x5>190.625</x5>
			<y5>505</y5>
			<x6>203.125</x6>
			<y6>511.25</y6>
			<x7>211.25</x7>
			<y7>510.625</y7>
			<x8>231.25</x8>
			<y8>499.375</y8>
			<x9>245</x9>
			<y9>474.375</y9>
			<x10>243.125</x10>
			<y10>467.5</y10>
			<x11>223.125</x11>
			<y11>466.25</y11>
		</polygon>
	</object>
	<object>
		<name>pothole</name>
		<pose>Unspecified</pose>
		<truncated>0</truncated>
		<difficult>0</difficult>
		<occluded>0</occluded>
		<bndbox>
			<xmin>222</xmin>
			<xmax>309</xmax>
			<ymin>377</ymin>
			<ymax>456</ymax>
		</bndbox>
		<polygon>
			<x1>287.5</x1>
			<y1>403.125</y1>
			<x2>282.5</x2>
			<y2>388.125</y2>
			<x3>271.875</x3>
			<y3>377.5</y3>
			<x4>263.125</x4>
			<y4>376.25</y4>
			<x5>230.625</x5>
			<y5>392.5</y5>
			<x6>221.25</x6>
			<y6>403.125</y6>
			<x7>222.5</x7>
			<y7>419.375</y7>
			<x8>254.375</x8>
			<y8>448.75</y8>
			<x9>274.375</x9>
			<y9>455</y9>
			<x10>285</x10>
			<y10>454.375</y10>
			<x11>306.25</x11>
			<y11>435.625</y11>
			<x12>307.5</x12>
			<y12>426.875</y12>
			<x13>303.75</x13>
			<y13>418.125</y13>
			<x14>287.5</x14>
			<y14>403.125</y14>
		</polygon>
	</object>
	<object>
		<name>pothole</name>
		<pose>Unspecified</pose>
		<truncated>0</truncated>
		<difficult>0</difficult>
		<occluded>0</occluded>
		<bndbox>
			<xmin>290</xmin>
			<xmax>359</xmax>
			<ymin>185</ymin>
			<ymax>319</ymax>
		</bndbox>
		<polygon>
			<x1>345</x1>
			<y1>213.125</y1>
			<x2>331.25</x2>
			<y2>193.125</y2>
			<x3>321.875</x3>
			<y3>183.75</y3>
			<x4>314.375</x4>
			<y4>183.75</y4>
			<x5>302.5</x5>
			<y5>193.125</y5>
			<x6>302.5</x6>
			<y6>199.375</y6>
			<x7>288.75</x7>
			<y7>214.375</y7>
			<x8>288.75</x8>
			<y8>255.625</y8>
			<x9>296.25</x9>
			<y9>300.625</y9>
			<x10>311.875</x10>
			<y10>317.5</y10>
			<x11>327.5</x11>
			<y11>318.125</y11>
			<x12>344.375</x12>
			<y12>313.75</y12>
			<x13>357.5</x13>
			<y13>301.875</y13>
			<x14>357.5</x14>
			<y14>244.375</y14>
			<x15>345</x15>
			<y15>213.125</y15>
		</polygon>
	</object>
	<object>
		<name>pothole</name>
		<pose>Unspecified</pose>
		<truncated>0</truncated>
		<difficult>0</difficult>
		<occluded>0</occluded>
		<bndbox>
			<xmin>242</xmin>
			<xmax>301</xmax>
			<ymin>332</ymin>
			<ymax>367</ymax>
		</bndbox>
		<polygon>
			<x1>283.125</x1>
			<y1>331.25</y1>
			<x2>258.125</x2>
			<y2>332.5</y2>
			<x3>250.625</x3>
			<y3>337.5</y3>
			<x4>241.25</x4>
			<y4>350.625</y4>
			<x5>241.25</x5>
			<y5>359.375</y5>
			<x6>248.125</x6>
			<y6>366.25</y6>
			<x7>260</x7>
			<y7>365.625</y7>
			<x8>290.625</x8>
			<y8>358.75</y8>
			<x9>300</x9>
			<y9>345.625</y9>
			<x10>300</x10>
			<y10>338.125</y10>
			<x11>283.125</x11>
			<y11>331.25</y11>
		</polygon>
	</object>
	<object>
		<name>pothole</name>
		<pose>Unspecified</pose>
		<truncated>0</truncated>
		<difficult>0</difficult>
		<occluded>0</occluded>
		<bndbox>
			<xmin>254</xmin>
			<xmax>370</xmax>
			<ymin>94</ymin>
			<ymax>169</ymax>
		</bndbox>
		<polygon>
			<x1>364.375</x1>
			<y1>150</y1>
			<x2>368.75</x2>
			<y2>145.625</y2>
			<x3>365</x3>
			<y3>113.125</y3>
			<x4>355.625</x4>
			<y4>96.25</y4>
			<x5>353.125</x5>
			<y5>101.25</y5>
			<x6>351.875</x6>
			<y6>97.5</y6>
			<x7>343.125</x7>
			<y7>97.5</y7>
			<x8>343.125</x8>
			<y8>92.5</y8>
			<x9>331.875</x9>
			<y9>93.75</y9>
			<x10>320</x10>
			<y10>100.625</y10>
			<x11>310.625</x11>
			<y11>118.75</y11>
			<x12>303.125</x12>
			<y12>113.75</y12>
			<x13>298.125</x13>
			<y13>116.25</y13>
			<x14>278.125</x14>
			<y14>111.25</y14>
			<x15>252.5</x15>
			<y15>123.125</y15>
			<x16>263.125</x16>
			<y16>137.5</y16>
			<x17>271.25</x17>
			<y17>139.375</y17>
			<x18>275.625</x18>
			<y18>148.75</y18>
			<x19>304.375</x19>
			<y19>167.5</y19>
			<x20>311.25</x20>
			<y20>168.125</y20>
			<x21>318.75</x21>
			<y21>161.875</y21>
			<x22>320.625</x22>
			<y22>138.75</y22>
			<x23>350.625</x23>
			<y23>151.25</y23>
			<x24>364.375</x24>
			<y24>150</y24>
		</polygon>
	</object>
	<object>
		<name>pothole</name>
		<pose>Unspecified</pose>
		<truncated>0</truncated>
		<difficult>0</difficult>
		<occluded>0</occluded>
		<bndbox>
			<xmin>358</xmin>
			<xmax>475</xmax>
			<ymin>1</ymin>
			<ymax>154</ymax>
		</bndbox>
		<polygon>
			<x1>473.75</x1>
			<y1>125.625</y1>
			<x2>471.25</x2>
			<y2>115.625</y2>
			<x3>446.875</x3>
			<y3>96.25</y3>
			<x4>416.25</x4>
			<y4>84.375</y4>
			<x5>413.75</x5>
			<y5>71.875</y5>
			<x6>425</x6>
			<y6>64.375</y6>
			<x7>421.875</x7>
			<y7>58.75</y7>
			<x8>415</x8>
			<y8>56.875</y8>
			<x9>413.75</x9>
			<y9>48.125</y9>
			<x10>407.5</x10>
			<y10>41.875</y10>
			<x11>403.75</x11>
			<y11>18.125</y11>
			<x12>395</x12>
			<y12>3.125</y12>
			<x13>391.875</x13>
			<y13>0</y13>
			<x14>356.875</x14>
			<y14>1.25</y14>
			<x15>357.5</x15>
			<y15>9.375</y15>
			<x16>375</x16>
			<y16>28.125</y16>
			<x17>400</x17>
			<y17>70.625</y17>
			<x18>403.75</x18>
			<y18>110.625</y18>
			<x19>412.5</x19>
			<y19>134.375</y19>
			<x20>428.125</x20>
			<y20>152.5</y20>
			<x21>440</x21>
			<y21>153.125</y21>
			<x22>447.5</x22>
			<y22>150.625</y22>
			<x23>447.5</x23>
			<y23>140.625</y23>
			<x24>443.125</x24>
			<y24>137.5</y24>
			<x25>473.75</x25>
			<y25>125.625</y25>
		</polygon>
	</object>
	<object>
		<name>pothole</name>
		<pose>Unspecified</pose>
		<truncated>0</truncated>
		<difficult>0</difficult>
		<occluded>0</occluded>
		<bndbox>
			<xmin>399</xmin>
			<xmax>484</xmax>
			<ymin>186</ymin>
			<ymax>304</ymax>
		</bndbox>
		<polygon>
			<x1>479.375</x1>
			<y1>238.75</y1>
			<x2>482.5</x2>
			<y2>231.875</y2>
			<x3>482.5</x3>
			<y3>210.625</y3>
			<x4>470</x4>
			<y4>191.875</y4>
			<x5>460.625</x5>
			<y5>185</y5>
			<x6>445.625</x6>
			<y6>186.25</y6>
			<x7>433.125</x7>
			<y7>193.75</y7>
			<x8>423.75</x8>
			<y8>210.625</y8>
			<x9>408.125</x9>
			<y9>217.5</y9>
			<x10>397.5</x10>
			<y10>233.125</y10>
			<x11>397.5</x11>
			<y11>258.125</y11>
			<x12>408.75</x12>
			<y12>288.125</y12>
			<x13>418.125</x13>
			<y13>301.25</y13>
			<x14>435</x14>
			<y14>303.125</y14>
			<x15>466.25</x15>
			<y15>294.375</y15>
			<x16>465</x16>
			<y16>265.625</y16>
			<x17>455</x17>
			<y17>241.875</y17>
			<x18>479.375</x18>
			<y18>238.75</y18>
		</polygon>
	</object>
	<object>
		<name>pothole</name>
		<pose>Unspecified</pose>
		<truncated>0</truncated>
		<difficult>0</difficult>
		<occluded>0</occluded>
		<bndbox>
			<xmin>377</xmin>
			<xmax>412</xmax>
			<ymin>305</ymin>
			<ymax>365</ymax>
		</bndbox>
		<polygon>
			<x1>406.875</x1>
			<y1>303.75</y1>
			<x2>396.875</x2>
			<y2>305</y2>
			<x3>376.25</x3>
			<y3>330.625</y3>
			<x4>377.5</x4>
			<y4>355.625</y4>
			<x5>388.125</x5>
			<y5>363.75</y5>
			<x6>397.5</x6>
			<y6>364.375</y6>
			<x7>405</x7>
			<y7>359.375</y7>
			<x8>405</x8>
			<y8>333.125</y8>
			<x9>411.25</x9>
			<y9>323.125</y9>
			<x10>406.875</x10>
			<y10>303.75</y10>
		</polygon>
	</object>
	<object>
		<name>pothole</name>
		<pose>Unspecified</pose>
		<truncated>0</truncated>
		<difficult>0</difficult>
		<occluded>0</occluded>
		<bndbox>
			<xmin>311</xmin>
			<xmax>362</xmax>
			<ymin>346</ymin>
			<ymax>405</ymax>
		</bndbox>
		<polygon>
			<x1>349.375</x1>
			<y1>358.75</y1>
			<x2>328.125</x2>
			<y2>345</y2>
			<x3>322.5</x3>
			<y3>358.125</y3>
			<x4>310</x4>
			<y4>366.875</y4>
			<x5>311.25</x5>
			<y5>395.625</y5>
			<x6>318.125</x6>
			<y6>403.75</y6>
			<x7>343.75</x7>
			<y7>404.375</y7>
			<x8>352.5</x8>
			<y8>399.375</y8>
			<x9>361.25</x9>
			<y9>383.125</y9>
			<x10>361.25</x10>
			<y10>371.875</y10>
			<x11>349.375</x11>
			<y11>358.75</y11>
		</polygon>
	</object>
	<object>
		<name>pothole</name>
		<pose>Unspecified</pose>
		<truncated>0</truncated>
		<difficult>0</difficult>
		<occluded>0</occluded>
		<bndbox>
			<xmin>351</xmin>
			<xmax>429</xmax>
			<ymin>381</ymin>
			<ymax>448</ymax>
		</bndbox>
		<polygon>
			<x1>408.125</x1>
			<y1>380</y1>
			<x2>388.125</x2>
			<y2>381.25</y2>
			<x3>363.125</x3>
			<y3>393.75</y3>
			<x4>361.25</x4>
			<y4>399.375</y4>
			<x5>350</x5>
			<y5>406.875</y5>
			<x6>351.25</x6>
			<y6>421.875</y6>
			<x7>363.125</x7>
			<y7>436.25</y7>
			<x8>381.875</x8>
			<y8>443.75</y8>
			<x9>407.5</x9>
			<y9>446.875</y9>
			<x10>423.75</x10>
			<y10>431.875</y10>
			<x11>427.5</x11>
			<y11>409.375</y11>
			<x12>423.75</x12>
			<y12>393.125</y12>
			<x13>408.125</x13>
			<y13>380</y13>
		</polygon>
	</object>
	<object>
		<name>pothole</name>
		<pose>Unspecified</pose>
		<truncated>0</truncated>
		<difficult>0</difficult>
		<occluded>0</occluded>
		<bndbox>
			<xmin>390</xmin>
			<xmax>640</xmax>
			<ymin>444</ymin>
			<ymax>641</ymax>
		</bndbox>
		<polygon>
			<x1>461.875</x1>
			<y1>611.25</y1>
			<x2>458.125</x2>
			<y2>613.75</y2>
			<x3>455</x3>
			<y3>610.625</y3>
			<x4>462.5</x4>
			<y4>606.875</y4>
			<x5>462.5</x5>
			<y5>590.625</y5>
			<x6>467.5</x6>
			<y6>588.125</y6>
			<x7>469.375</x7>
			<y7>568.75</y7>
			<x8>473.125</x8>
			<y8>585</y8>
			<x9>477.5</x9>
			<y9>579.375</y9>
			<x10>473.75</x10>
			<y10>573.125</y10>
			<x11>478.125</x11>
			<y11>571.25</y11>
			<x12>482.5</x12>
			<y12>583.125</y12>
			<x13>490</x13>
			<y13>588.125</y13>
			<x14>491.25</x14>
			<y14>618.125</y14>
			<x15>494.375</x15>
			<y15>621.25</y15>
			<x16>502.5</x16>
			<y16>616.875</y16>
			<x17>496.25</x17>
			<y17>611.875</y17>
			<x18>505</x18>
			<y18>606.875</y18>
			<x19>503.75</x19>
			<y19>603.125</y19>
			<x20>508.125</x20>
			<y20>598.75</y20>
			<x21>526.875</x21>
			<y21>590</y21>
			<x22>550.625</x22>
			<y22>590</y22>
			<x23>556.875</x23>
			<y23>586.25</y23>
			<x24>609.375</x24>
			<y24>590</y24>
			<x25>631.875</x25>
			<y25>580</y25>
			<x26>635</x26>
			<y26>584.375</y26>
			<x27>630</x27>
			<y27>586.875</y27>
			<x28>637.5</x28>
			<y28>586.875</y28>
			<x29>639.375</x29>
			<y29>447.5</y29>
			<x30>569.375</x30>
			<y30>447.5</y30>
			<x31>546.875</x31>
			<y31>442.5</y31>
			<x32>535</x32>
			<y32>449.375</y32>
			<x33>533.75</x33>
			<y33>456.875</y33>
			<x34>515</x34>
			<y34>474.375</y34>
			<x35>512.5</x35>
			<y35>483.125</y35>
			<x36>503.125</x36>
			<y36>492.5</y36>
			<x37>489.375</x37>
			<y37>485</y37>
			<x38>481.875</x38>
			<y38>473.75</y38>
			<x39>474.375</x39>
			<y39>473.75</y39>
			<x40>468.125</x40>
			<y40>487.5</y40>
			<x41>466.25</x41>
			<y41>476.875</y41>
			<x42>470</x42>
			<y42>474.375</y42>
			<x43>470</x43>
			<y43>466.875</y43>
			<x44>454.375</x44>
			<y44>455</y44>
			<x45>443.125</x45>
			<y45>456.25</y45>
			<x46>416.25</x46>
			<y46>478.125</y46>
			<x47>388.75</x47>
			<y47>545.625</y47>
			<x48>390</x48>
			<y48>580.625</y48>
			<x49>403.75</x49>
			<y49>590.625</y49>
			<x50>407.5</x50>
			<y50>600.625</y50>
			<x51>402.5</x51>
			<y51>639.375</y51>
			<x52>431.875</x52>
			<y52>640</y52>
			<x53>437.5</x53>
			<y53>636.875</y53>
			<x54>433.75</x54>
			<y54>631.875</y54>
			<x55>438.125</x55>
			<y55>628.75</y55>
			<x56>441.875</x56>
			<y56>640</y56>
			<x57>447.5</x57>
			<y57>638.125</y57>
			<x58>442.5</x58>
			<y58>631.875</y58>
			<x59>445.625</x59>
			<y59>630</y59>
			<x60>450</x60>
			<y60>630.625</y60>
			<x61>450.625</x61>
			<y61>640</y61>
			<x62>467.5</x62>
			<y62>639.375</y62>
			<x63>462.5</x63>
			<y63>633.125</y63>
			<x64>468.75</x64>
			<y64>628.125</y64>
			<x65>466.25</x65>
			<y65>616.875</y65>
			<x66>461.875</x66>
			<y66>611.25</y66>
		</polygon>
	</object>
	<object>
		<name>pothole</name>
		<pose>Unspecified</pose>
		<truncated>0</truncated>
		<difficult>0</difficult>
		<occluded>0</occluded>
		<bndbox>
			<xmin>391</xmin>
			<xmax>480</xmax>
			<ymin>457</ymin>
			<ymax>641</ymax>
		</bndbox>
		<polygon>
			<x1>476.25</x1>
			<y1>563.125</y1>
			<x2>476.25</x2>
			<y2>533.125</y2>
			<x3>456.25</x3>
			<y3>500.625</y3>
			<x4>457.5</x4>
			<y4>480.625</y4>
			<x5>467.5</x5>
			<y5>463.125</y5>
			<x6>456.875</x6>
			<y6>456.25</y6>
			<x7>446.875</x7>
			<y7>456.25</y7>
			<x8>415</x8>
			<y8>481.875</y8>
			<x9>390</x9>
			<y9>543.125</y9>
			<x10>390</x10>
			<y10>578.125</y10>
			<x11>403.75</x11>
			<y11>590.625</y11>
			<x12>408.75</x12>
			<y12>604.375</y12>
			<x13>401.25</x13>
			<y13>621.875</y13>
			<x14>400</x14>
			<y14>636.875</y14>
			<x15>401.875</x15>
			<y15>640</y15>
			<x16>478.75</x16>
			<y16>639.375</y16>
			<x17>477.5</x17>
			<y17>618.125</y17>
			<x18>466.25</x18>
			<y18>601.875</y18>
			<x19>466.25</x19>
			<y19>585.625</y19>
			<x20>476.25</x20>
			<y20>563.125</y20>
		</polygon>
	</object>
	<object>
		<name>pothole</name>
		<pose>Unspecified</pose>
		<truncated>0</truncated>
		<difficult>0</difficult>
		<occluded>0</occluded>
		<bndbox>
			<xmin>300</xmin>
			<xmax>390</xmax>
			<ymin>474</ymin>
			<ymax>552</ymax>
		</bndbox>
		<polygon>
			<x1>375.625</x1>
			<y1>472.5</y1>
			<x2>340.625</x2>
			<y2>472.5</y2>
			<x3>336.875</x3>
			<y3>486.25</y3>
			<x4>313.125</x4>
			<y4>486.25</y4>
			<x5>300</x5>
			<y5>498.125</y5>
			<x6>298.75</x6>
			<y6>523.125</y6>
			<x7>305.625</x7>
			<y7>532.5</y7>
			<x8>325.625</x8>
			<y8>533.75</y8>
			<x9>343.125</x9>
			<y9>545</y9>
			<x10>365</x10>
			<y10>550.625</y10>
			<x11>373.75</x11>
			<y11>541.875</y11>
			<x12>368.75</x12>
			<y12>516.875</y12>
			<x13>388.75</x13>
			<y13>499.375</y13>
			<x14>375.625</x14>
			<y14>472.5</y14>
		</polygon>
	</object>
	<object>
		<name>pothole</name>
		<pose>Unspecified</pose>
		<truncated>0</truncated>
		<difficult>0</difficult>
		<occluded>0</occluded>
		<bndbox>
			<xmin>332</xmin>
			<xmax>379</xmax>
			<ymin>610</ymin>
			<ymax>641</ymax>
		</bndbox>
		<polygon>
			<x1>331.25</x1>
			<y1>624.375</y1>
			<x2>330.625</x2>
			<y2>640</y2>
			<x3>371.25</x3>
			<y3>639.375</y3>
			<x4>377.5</x4>
			<y4>625.625</y4>
			<x5>374.375</x5>
			<y5>608.75</y5>
			<x6>359.375</x6>
			<y6>608.75</y6>
			<x7>331.25</x7>
			<y7>624.375</y7>
		</polygon>
	</object>
	<object>
		<name>pothole</name>
		<pose>Unspecified</pose>
		<truncated>0</truncated>
		<difficult>0</difficult>
		<occluded>0</occluded>
		<bndbox>
			<xmin>480</xmin>
			<xmax>545</xmax>
			<ymin>369</ymin>
			<ymax>428</ymax>
		</bndbox>
		<polygon>
			<x1>540</x1>
			<y1>394.375</y1>
			<x2>543.75</x2>
			<y2>388.125</y2>
			<x3>543.75</x3>
			<y3>371.875</y3>
			<x4>540.625</x4>
			<y4>368.75</y4>
			<x5>521.875</x5>
			<y5>367.5</y5>
			<x6>514.375</x6>
			<y6>387.5</y6>
			<x7>499.375</x7>
			<y7>381.25</y7>
			<x8>486.25</x8>
			<y8>388.125</y8>
			<x9>478.75</x9>
			<y9>406.875</y9>
			<x10>478.75</x10>
			<y10>419.375</y10>
			<x11>488.75</x11>
			<y11>426.875</y11>
			<x12>504.375</x12>
			<y12>422.5</y12>
			<x13>510.625</x13>
			<y13>406.25</y13>
			<x14>528.125</x14>
			<y14>403.75</y14>
			<x15>540</x15>
			<y15>394.375</y15>
		</polygon>
	</object>
	<object>
		<name>pothole</name>
		<pose>Unspecified</pose>
		<truncated>0</truncated>
		<difficult>0</difficult>
		<occluded>0</occluded>
		<bndbox>
			<xmin>490</xmin>
			<xmax>549</xmax>
			<ymin>185</ymin>
			<ymax>235</ymax>
		</bndbox>
		<polygon>
			<x1>491.875</x1>
			<y1>185</y1>
			<x2>488.75</x2>
			<y2>188.125</y2>
			<x3>488.75</x3>
			<y3>206.875</y3>
			<x4>508.125</x4>
			<y4>227.5</y4>
			<x5>519.375</x5>
			<y5>233.75</y5>
			<x6>531.25</x6>
			<y6>233.125</y6>
			<x7>547.5</x7>
			<y7>220.625</y7>
			<x8>547.5</x8>
			<y8>186.875</y8>
			<x9>541.875</x9>
			<y9>183.75</y9>
			<x10>491.875</x10>
			<y10>185</y10>
		</polygon>
	</object>
	<object>
		<name>pothole</name>
		<pose>Unspecified</pose>
		<truncated>0</truncated>
		<difficult>0</difficult>
		<occluded>0</occluded>
		<bndbox>
			<xmin>548</xmin>
			<xmax>587</xmax>
			<ymin>227</ymin>
			<ymax>257</ymax>
		</bndbox>
		<polygon>
			<x1>558.125</x1>
			<y1>237.5</y1>
			<x2>546.875</x2>
			<y2>226.25</y2>
			<x3>552.5</x3>
			<y3>254.375</y3>
			<x4>565</x4>
			<y4>255.625</y4>
			<x5>585.625</x5>
			<y5>253.75</y5>
			<x6>586.25</x6>
			<y6>234.375</y6>
			<x7>576.875</x7>
			<y7>230</y7>
			<x8>558.125</x8>
			<y8>237.5</y8>
		</polygon>
	</object>
	<object>
		<name>pothole</name>
		<pose>Unspecified</pose>
		<truncated>0</truncated>
		<difficult>0</difficult>
		<occluded>0</occluded>
		<bndbox>
			<xmin>486</xmin>
			<xmax>530</xmax>
			<ymin>245</ymin>
			<ymax>275</ymax>
		</bndbox>
		<polygon>
			<x1>505.625</x1>
			<y1>243.75</y1>
			<x2>486.875</x2>
			<y2>245</y2>
			<x3>485</x3>
			<y3>256.875</y3>
			<x4>488.75</x4>
			<y4>273.125</y4>
			<x5>500</x5>
			<y5>274.375</y5>
			<x6>523.125</x6>
			<y6>267.5</y6>
			<x7>528.75</x7>
			<y7>261.875</y7>
			<x8>528.75</x8>
			<y8>255.625</y8>
			<x9>505.625</x9>
			<y9>243.75</y9>
		</polygon>
	</object>
	<object>
		<name>pothole</name>
		<pose>Unspecified</pose>
		<truncated>0</truncated>
		<difficult>0</difficult>
		<occluded>0</occluded>
		<bndbox>
			<xmin>602</xmin>
			<xmax>631</xmax>
			<ymin>224</ymin>
			<ymax>253</ymax>
		</bndbox>
		<polygon>
			<x1>618.125</x1>
			<y1>223.75</y1>
			<x2>601.25</x2>
			<y2>241.875</y2>
			<x3>605.625</x3>
			<y3>248.75</y3>
			<x4>621.25</x4>
			<y4>251.875</y4>
			<x5>630</x5>
			<y5>243.125</y5>
			<x6>630</x6>
			<y6>228.125</y6>
			<x7>624.375</x7>
			<y7>222.5</y7>
			<x8>618.125</x8>
			<y8>223.75</y8>
		</polygon>
	</object>
	<object>
		<name>pothole</name>
		<pose>Unspecified</pose>
		<truncated>0</truncated>
		<difficult>0</difficult>
		<occluded>0</occluded>
		<bndbox>
			<xmin>608</xmin>
			<xmax>614</xmax>
			<ymin>195</ymin>
			<ymax>210</ymax>
		</bndbox>
		<polygon>
			<x1>612.5</x1>
			<y1>198.125</y1>
			<x2>606.875</x2>
			<y2>193.75</y2>
			<x3>611.25</x3>
			<y3>209.375</y3>
			<x4>612.5</x4>
			<y4>198.125</y4>
		</polygon>
	</object>
	<object>
		<name>pothole</name>
		<pose>Unspecified</pose>
		<truncated>0</truncated>
		<difficult>0</difficult>
		<occluded>0</occluded>
		<bndbox>
			<xmin>580</xmin>
			<xmax>592</xmax>
			<ymin>200</ymin>
			<ymax>220</ymax>
		</bndbox>
		<polygon>
			<x1>578.75</x1>
			<y1>214.375</y1>
			<x2>583.125</x2>
			<y2>218.75</y2>
			<x3>590</x3>
			<y3>218.125</y3>
			<x4>591.25</x4>
			<y4>203.125</y4>
			<x5>581.875</x5>
			<y5>198.75</y5>
			<x6>578.75</x6>
			<y6>200.625</y6>
			<x7>578.75</x7>
			<y7>214.375</y7>
		</polygon>
	</object>
	<object>
		<name>pothole</name>
		<pose>Unspecified</pose>
		<truncated>0</truncated>
		<difficult>0</difficult>
		<occluded>0</occluded>
		<bndbox>
			<xmin>461</xmin>
			<xmax>641</xmax>
			<ymin>1</ymin>
			<ymax>88</ymax>
		</bndbox>
		<polygon>
			<x1>518.125</x1>
			<y1>0</y1>
			<x2>518.75</x2>
			<y2>25.625</y2>
			<x3>541.875</x3>
			<y3>35</y3>
			<x4>543.125</x4>
			<y4>43.75</y4>
			<x5>490.625</x5>
			<y5>50</y5>
			<x6>488.125</x6>
			<y6>55</y6>
			<x7>483.125</x7>
			<y7>50</y7>
			<x8>460</x8>
			<y8>51.875</y8>
			<x9>470</x9>
			<y9>76.875</y9>
			<x10>475.625</x10>
			<y10>81.25</y10>
			<x11>489.375</x11>
			<y11>82.5</y11>
			<x12>498.125</x12>
			<y12>78.75</y12>
			<x13>513.125</x13>
			<y13>85</y13>
			<x14>515.625</x14>
			<y14>76.25</y14>
			<x15>519.375</x15>
			<y15>80</y15>
			<x16>533.125</x16>
			<y16>80</y16>
			<x17>546.875</x17>
			<y17>71.25</y17>
			<x18>565</x18>
			<y18>86.875</y18>
			<x19>586.875</x19>
			<y19>81.25</y19>
			<x20>640</x20>
			<y20>84.375</y20>
			<x21>639.375</x21>
			<y21>0</y21>
			<x22>518.125</x22>
			<y22>0</y22>
		</polygon>
	</object>
	<object>
		<name>pothole</name>
		<pose>Unspecified</pose>
		<truncated>0</truncated>
		<difficult>0</difficult>
		<occluded>0</occluded>
		<bndbox>
			<xmin>514</xmin>
			<xmax>545</xmax>
			<ymin>95</ymin>
			<ymax>127</ymax>
		</bndbox>
		<polygon>
			<x1>513.125</x1>
			<y1>93.75</y1>
			<x2>512.5</x2>
			<y2>124.375</y2>
			<x3>532.5</x3>
			<y3>125.625</y3>
			<x4>543.75</x4>
			<y4>121.875</y4>
			<x5>543.75</x5>
			<y5>110.625</y5>
			<x6>534.375</x6>
			<y6>102.5</y6>
			<x7>513.125</x7>
			<y7>93.75</y7>
		</polygon>
	</object>
	<object>
		<name>pothole</name>
		<pose>Unspecified</pose>
		<truncated>0</truncated>
		<difficult>0</difficult>
		<occluded>0</occluded>
		<bndbox>
			<xmin>560</xmin>
			<xmax>576</xmax>
			<ymin>92</ymin>
			<ymax>119</ymax>
		</bndbox>
		<polygon>
			<x1>558.75</x1>
			<y1>111.875</y1>
			<x2>570</x2>
			<y2>118.125</y2>
			<x3>575</x3>
			<y3>96.875</y3>
			<x4>568.125</x4>
			<y4>91.25</y4>
			<x5>558.75</x5>
			<y5>98.125</y5>
			<x6>558.75</x6>
			<y6>111.875</y6>
		</polygon>
	</object>
	<object>
		<name>pothole</name>
		<pose>Unspecified</pose>
		<truncated>0</truncated>
		<difficult>0</difficult>
		<occluded>0</occluded>
		<bndbox>
			<xmin>587</xmin>
			<xmax>619</xmax>
			<ymin>85</ymin>
			<ymax>129</ymax>
		</bndbox>
		<polygon>
			<x1>602.5</x1>
			<y1>88.125</y1>
			<x2>596.875</x2>
			<y2>83.75</y2>
			<x3>590.625</x3>
			<y3>85</y3>
			<x4>586.25</x4>
			<y4>90.625</y4>
			<x5>590</x5>
			<y5>124.375</y5>
			<x6>595.625</x6>
			<y6>127.5</y6>
			<x7>616.25</x7>
			<y7>126.875</y7>
			<x8>617.5</x8>
			<y8>106.875</y8>
			<x9>611.875</x9>
			<y9>106.25</y9>
			<x10>608.125</x10>
			<y10>111.25</y10>
			<x11>602.5</x11>
			<y11>88.125</y11>
		</polygon>
	</object>
</annotation>
