<annotation>
	<folder></folder>
	<filename>T111505_jpg.rf.ad4064d2c4939d429a322995f6609a20.jpg</filename>
	<path>T111505_jpg.rf.ad4064d2c4939d429a322995f6609a20.jpg</path>
	<source>
		<database>roboflow.com</database>
	</source>
	<size>
		<width>640</width>
		<height>640</height>
		<depth>3</depth>
	</size>
	<segmented>0</segmented>
	<object>
		<name>rail</name>
		<pose>Unspecified</pose>
		<truncated>0</truncated>
		<difficult>0</difficult>
		<occluded>0</occluded>
		<bndbox>
			<xmin>8</xmin>
			<xmax>434</xmax>
			<ymin>1</ymin>
			<ymax>634</ymax>
		</bndbox>
		<polygon>
			<x1>95.549845</x1>
			<y1>0</y1>
			<x2>7.345452</x2>
			<y2>4.912523</y2>
			<x3>7.345452</x3>
			<y3>41.509106</y3>
			<x4>20.006186</x4>
			<y4>602.199512</y4>
			<x5>207.462881</x5>
			<y5>632.619251</y5>
			<x6>207.71609</x6>
			<y6>633</y6>
			<x7>209.903486</x7>
			<y7>633</y7>
			<x8>431.331957</x8>
			<y8>299.01604</y8>
			<x9>433</x9>
			<y9>236.809509</y9>
			<x10>433</x10>
			<y10>172.483197</y10>
			<x11>393.570924</x11>
			<y11>154.015217</y11>
			<x12>176.256334</x12>
			<y12>0</y12>
			<x13>95.549845</x13>
			<y13>0</y13>
		</polygon>
	</object>
</annotation>
